{
"meta":{"test_sets":[],"test_metrics":[],"learn_metrics":[{"best_value":"Min","name":"RMSE"}],"launch_mode":"Train","parameters":"","iteration_count":300,"learn_sets":["learn"],"name":"experiment"},
"iterations":[
{"learn":[7.980250955],"iteration":0,"passed_time":0.1816437082,"remaining_time":54.31146874},
{"learn":[7.254754485],"iteration":1,"passed_time":0.3564059915,"remaining_time":53.10449273},
{"learn":[6.605782215],"iteration":2,"passed_time":0.49422945,"remaining_time":48.92871555},
{"learn":[6.026763713],"iteration":3,"passed_time":0.5913259501,"remaining_time":43.7581203},
{"learn":[5.50413982],"iteration":4,"passed_time":0.694124526,"remaining_time":40.95334703},
{"learn":[5.035268416],"iteration":5,"passed_time":0.7954789993,"remaining_time":38.97847097},
{"learn":[4.614031907],"iteration":6,"passed_time":0.9009962364,"remaining_time":37.71312818},
{"learn":[4.241843425],"iteration":7,"passed_time":0.9780966788,"remaining_time":35.70052878},
{"learn":[3.909789571],"iteration":8,"passed_time":1.075169512,"remaining_time":34.76381422},
{"learn":[3.619256662],"iteration":9,"passed_time":1.161536203,"remaining_time":33.68454987},
{"learn":[3.362579496],"iteration":10,"passed_time":1.252413995,"remaining_time":32.90433132},
{"learn":[3.130083002],"iteration":11,"passed_time":1.340790004,"remaining_time":32.17896009},
{"learn":[2.925899043],"iteration":12,"passed_time":1.42215892,"remaining_time":31.39689307},
{"learn":[2.749319011],"iteration":13,"passed_time":1.510959684,"remaining_time":30.86674784},
{"learn":[2.595331829],"iteration":14,"passed_time":1.609832166,"remaining_time":30.58681116},
{"learn":[2.459090457],"iteration":15,"passed_time":1.68265676,"remaining_time":29.86715749},
{"learn":[2.339402324],"iteration":16,"passed_time":1.774466732,"remaining_time":29.53965206},
{"learn":[2.237566822],"iteration":17,"passed_time":1.864007673,"remaining_time":29.20278688},
{"learn":[2.146658173],"iteration":18,"passed_time":1.948784926,"remaining_time":28.82150338},
{"learn":[2.069498082],"iteration":19,"passed_time":2.039318338,"remaining_time":28.55045674},
{"learn":[2.002840168],"iteration":20,"passed_time":2.135953416,"remaining_time":28.37766681},
{"learn":[1.939995666],"iteration":21,"passed_time":2.21531468,"remaining_time":27.99352186},
{"learn":[1.885097456],"iteration":22,"passed_time":2.300265393,"remaining_time":27.70319626},
{"learn":[1.835490003],"iteration":23,"passed_time":2.364782793,"remaining_time":27.19500212},
{"learn":[1.795252023],"iteration":24,"passed_time":2.456571223,"remaining_time":27.02228345},
{"learn":[1.758100545],"iteration":25,"passed_time":2.541282475,"remaining_time":26.78120762},
{"learn":[1.725021547],"iteration":26,"passed_time":2.626795196,"remaining_time":26.55981809},
{"learn":[1.695871461],"iteration":27,"passed_time":2.711766826,"remaining_time":26.34287774},
{"learn":[1.671062677],"iteration":28,"passed_time":2.796667622,"remaining_time":26.13437675},
{"learn":[1.649290884],"iteration":29,"passed_time":2.87129049,"remaining_time":25.84161441},
{"learn":[1.629763207],"iteration":30,"passed_time":2.938124296,"remaining_time":25.49533663},
{"learn":[1.611338035],"iteration":31,"passed_time":3.003127077,"remaining_time":25.15118927},
{"learn":[1.594866379],"iteration":32,"passed_time":3.097494874,"remaining_time":25.06154944},
{"learn":[1.580759747],"iteration":33,"passed_time":3.198912182,"remaining_time":25.02678354},
{"learn":[1.56848924],"iteration":34,"passed_time":3.302509227,"remaining_time":25.00471272},
{"learn":[1.557605509],"iteration":35,"passed_time":3.379036161,"remaining_time":24.77959852},
{"learn":[1.547538908],"iteration":36,"passed_time":3.475020272,"remaining_time":24.70081977},
{"learn":[1.539232669],"iteration":37,"passed_time":3.567143581,"remaining_time":24.59451627},
{"learn":[1.530310089],"iteration":38,"passed_time":3.640441972,"remaining_time":24.36295782},
{"learn":[1.522053764],"iteration":39,"passed_time":3.712268428,"remaining_time":24.12974478},
{"learn":[1.514249002],"iteration":40,"passed_time":3.796739843,"remaining_time":23.9842834},
{"learn":[1.508397253],"iteration":41,"passed_time":3.897549726,"remaining_time":23.94209118},
{"learn":[1.502461086],"iteration":42,"passed_time":3.990846051,"remaining_time":23.85226593},
{"learn":[1.497674949],"iteration":43,"passed_time":4.093781003,"remaining_time":23.8183622},
{"learn":[1.493861358],"iteration":44,"passed_time":4.182400807,"remaining_time":23.70027124},
{"learn":[1.487187489],"iteration":45,"passed_time":4.277153776,"remaining_time":23.61732737},
{"learn":[1.482385917],"iteration":46,"passed_time":4.381310412,"remaining_time":23.58450073},
{"learn":[1.478725612],"iteration":47,"passed_time":4.480993321,"remaining_time":23.52521494},
{"learn":[1.474296044],"iteration":48,"passed_time":4.576523467,"remaining_time":23.44300796},
{"learn":[1.469690125],"iteration":49,"passed_time":4.671613941,"remaining_time":23.3580697},
{"learn":[1.464758098],"iteration":50,"passed_time":4.762112311,"remaining_time":23.25031305},
{"learn":[1.461439753],"iteration":51,"passed_time":4.871316889,"remaining_time":23.23243439},
{"learn":[1.457102795],"iteration":52,"passed_time":4.972944366,"remaining_time":23.17579733},
{"learn":[1.452666269],"iteration":53,"passed_time":5.048183992,"remaining_time":22.99728263},
{"learn":[1.449372933],"iteration":54,"passed_time":5.128461685,"remaining_time":22.84496569},
{"learn":[1.444936897],"iteration":55,"passed_time":5.197399894,"remaining_time":22.64581382},
{"learn":[1.440639067],"iteration":56,"passed_time":5.273053567,"remaining_time":22.47985994},
{"learn":[1.437653937],"iteration":57,"passed_time":5.374816754,"remaining_time":22.42595956},
{"learn":[1.433599717],"iteration":58,"passed_time":5.472130049,"remaining_time":22.35226003},
{"learn":[1.429079224],"iteration":59,"passed_time":5.562689378,"remaining_time":22.25075751},
{"learn":[1.426473304],"iteration":60,"passed_time":5.652574283,"remaining_time":22.14697137},
{"learn":[1.423267882],"iteration":61,"passed_time":5.749281986,"remaining_time":22.0698244},
{"learn":[1.419495121],"iteration":62,"passed_time":5.844003246,"remaining_time":21.98458364},
{"learn":[1.41619951],"iteration":63,"passed_time":5.93714436,"remaining_time":21.89321983},
{"learn":[1.413228766],"iteration":64,"passed_time":6.03262238,"remaining_time":21.81025014},
{"learn":[1.410212502],"iteration":65,"passed_time":6.145701801,"remaining_time":21.78930639},
{"learn":[1.406756818],"iteration":66,"passed_time":6.242766176,"remaining_time":21.70991819},
{"learn":[1.40444574],"iteration":67,"passed_time":6.33166415,"remaining_time":21.60214828},
{"learn":[1.401919948],"iteration":68,"passed_time":6.403575149,"remaining_time":21.43805593},
{"learn":[1.398617439],"iteration":69,"passed_time":6.495663749,"remaining_time":21.34289517},
{"learn":[1.395429146],"iteration":70,"passed_time":6.573239281,"remaining_time":21.2010112},
{"learn":[1.392467853],"iteration":71,"passed_time":6.668655758,"remaining_time":21.1174099},
{"learn":[1.389475484],"iteration":72,"passed_time":6.742006568,"remaining_time":20.96486974},
{"learn":[1.387237275],"iteration":73,"passed_time":6.817083858,"remaining_time":20.81974259},
{"learn":[1.385276019],"iteration":74,"passed_time":6.900895306,"remaining_time":20.70268592},
{"learn":[1.382774025],"iteration":75,"passed_time":6.996719206,"remaining_time":20.62190924},
{"learn":[1.380139533],"iteration":76,"passed_time":7.09031116,"remaining_time":20.53427777},
{"learn":[1.378098659],"iteration":77,"passed_time":7.171208527,"remaining_time":20.41036273},
{"learn":[1.376134082],"iteration":78,"passed_time":7.265465698,"remaining_time":20.32491037},
{"learn":[1.373059366],"iteration":79,"passed_time":7.353684455,"remaining_time":20.22263225},
{"learn":[1.371020729],"iteration":80,"passed_time":7.440833489,"remaining_time":20.11780906},
{"learn":[1.368774481],"iteration":81,"passed_time":7.517657011,"remaining_time":19.9859662},
{"learn":[1.366794744],"iteration":82,"passed_time":7.615789317,"remaining_time":19.91116002},
{"learn":[1.364975806],"iteration":83,"passed_time":7.712051389,"remaining_time":19.83098929},
{"learn":[1.362831977],"iteration":84,"passed_time":7.810907121,"remaining_time":19.75700036},
{"learn":[1.36108767],"iteration":85,"passed_time":7.903615771,"remaining_time":19.66713692},
{"learn":[1.359405919],"iteration":86,"passed_time":7.997854358,"remaining_time":19.58095377},
{"learn":[1.35765936],"iteration":87,"passed_time":8.078273303,"remaining_time":19.46129478},
{"learn":[1.355772518],"iteration":88,"passed_time":8.180853668,"remaining_time":19.39505757},
{"learn":[1.354060649],"iteration":89,"passed_time":8.288452766,"remaining_time":19.33972312},
{"learn":[1.352071541],"iteration":90,"passed_time":8.38973878,"remaining_time":19.26874071},
{"learn":[1.350566963],"iteration":91,"passed_time":8.466215756,"remaining_time":19.14100953},
{"learn":[1.348650039],"iteration":92,"passed_time":8.567318017,"remaining_time":19.06919172},
{"learn":[1.346848668],"iteration":93,"passed_time":8.662904622,"remaining_time":18.98466332},
{"learn":[1.345528012],"iteration":94,"passed_time":8.759691493,"remaining_time":18.90249217},
{"learn":[1.343838239],"iteration":95,"passed_time":8.846739235,"remaining_time":18.79932087},
{"learn":[1.342287981],"iteration":96,"passed_time":8.942719761,"remaining_time":18.71517641},
{"learn":[1.340766019],"iteration":97,"passed_time":9.038240657,"remaining_time":18.62984299},
{"learn":[1.339341395],"iteration":98,"passed_time":9.1222699,"remaining_time":18.52097222},
{"learn":[1.338006093],"iteration":99,"passed_time":9.21048549,"remaining_time":18.42097098},
{"learn":[1.336798006],"iteration":100,"passed_time":9.306365308,"remaining_time":18.33630392},
{"learn":[1.335795022],"iteration":101,"passed_time":9.389283827,"remaining_time":18.22625684},
{"learn":[1.334282249],"iteration":102,"passed_time":9.49044734,"remaining_time":18.15163229},
{"learn":[1.332996234],"iteration":103,"passed_time":9.567649784,"remaining_time":18.03133998},
{"learn":[1.331811598],"iteration":104,"passed_time":9.654277769,"remaining_time":17.929373},
{"learn":[1.330372329],"iteration":105,"passed_time":9.757962024,"remaining_time":17.85891163},
{"learn":[1.32926065],"iteration":106,"passed_time":9.858634863,"remaining_time":17.78239746},
{"learn":[1.327996677],"iteration":107,"passed_time":9.937107532,"remaining_time":17.66596895},
{"learn":[1.326713518],"iteration":108,"passed_time":10.03188488,"remaining_time":17.57880744},
{"learn":[1.32554653],"iteration":109,"passed_time":10.12899146,"remaining_time":17.4955307},
{"learn":[1.324229445],"iteration":110,"passed_time":10.20545114,"remaining_time":17.37684924},
{"learn":[1.323313964],"iteration":111,"passed_time":10.31896353,"remaining_time":17.32111735},
{"learn":[1.322238893],"iteration":112,"passed_time":10.38901996,"remaining_time":17.19244896},
{"learn":[1.321118781],"iteration":113,"passed_time":10.49030664,"remaining_time":17.11576347},
{"learn":[1.320116441],"iteration":114,"passed_time":10.57505289,"remaining_time":17.01204161},
{"learn":[1.318839818],"iteration":115,"passed_time":10.66535272,"remaining_time":16.91745604},
{"learn":[1.3182738],"iteration":116,"passed_time":10.7465013,"remaining_time":16.80863024},
{"learn":[1.317177479],"iteration":117,"passed_time":10.82012415,"remaining_time":16.68866607},
{"learn":[1.316261457],"iteration":118,"passed_time":10.93089079,"remaining_time":16.62597675},
{"learn":[1.315475348],"iteration":119,"passed_time":11.02858822,"remaining_time":16.54288233},
{"learn":[1.314342575],"iteration":120,"passed_time":11.11328326,"remaining_time":16.4403116},
{"learn":[1.313281219],"iteration":121,"passed_time":11.20390143,"remaining_time":16.34667585},
{"learn":[1.312125141],"iteration":122,"passed_time":11.29715992,"remaining_time":16.25688866},
{"learn":[1.311409344],"iteration":123,"passed_time":11.41134335,"remaining_time":16.1967454},
{"learn":[1.31033099],"iteration":124,"passed_time":11.50893607,"remaining_time":16.11251049},
{"learn":[1.309434878],"iteration":125,"passed_time":11.58476395,"remaining_time":15.99800736},
{"learn":[1.308393535],"iteration":126,"passed_time":11.66621062,"remaining_time":15.89176722},
{"learn":[1.307497862],"iteration":127,"passed_time":11.76150805,"remaining_time":15.80452645},
{"learn":[1.306688111],"iteration":128,"passed_time":11.83631801,"remaining_time":15.69000294},
{"learn":[1.305857696],"iteration":129,"passed_time":11.92216707,"remaining_time":15.59052616},
{"learn":[1.305186113],"iteration":130,"passed_time":12.02792876,"remaining_time":15.51694627},
{"learn":[1.304338357],"iteration":131,"passed_time":12.13940837,"remaining_time":15.45015611},
{"learn":[1.303583724],"iteration":132,"passed_time":12.23866828,"remaining_time":15.36735039},
{"learn":[1.303005469],"iteration":133,"passed_time":12.34130643,"remaining_time":15.28848409},
{"learn":[1.302237298],"iteration":134,"passed_time":12.43278161,"remaining_time":15.19562197},
{"learn":[1.30163332],"iteration":135,"passed_time":12.50809853,"remaining_time":15.08329528},
{"learn":[1.300939681],"iteration":136,"passed_time":12.59059733,"remaining_time":14.98005376},
{"learn":[1.300285895],"iteration":137,"passed_time":12.69475439,"remaining_time":14.90253776},
{"learn":[1.299499785],"iteration":138,"passed_time":12.76786936,"remaining_time":14.78868321},
{"learn":[1.298745283],"iteration":139,"passed_time":12.8587864,"remaining_time":14.69575589},
{"learn":[1.29797752],"iteration":140,"passed_time":12.96446535,"remaining_time":14.61950348},
{"learn":[1.297333234],"iteration":141,"passed_time":13.06522827,"remaining_time":14.53736667},
{"learn":[1.296610935],"iteration":142,"passed_time":13.1412372,"remaining_time":14.42779189},
{"learn":[1.295828515],"iteration":143,"passed_time":13.23165615,"remaining_time":14.33429417},
{"learn":[1.295325129],"iteration":144,"passed_time":13.33693522,"remaining_time":14.25672386},
{"learn":[1.294668888],"iteration":145,"passed_time":13.42670583,"remaining_time":14.16241574},
{"learn":[1.294237291],"iteration":146,"passed_time":13.5089268,"remaining_time":14.06031157},
{"learn":[1.293663353],"iteration":147,"passed_time":13.60458816,"remaining_time":13.97227973},
{"learn":[1.293081896],"iteration":148,"passed_time":13.69736427,"remaining_time":13.8812215},
{"learn":[1.29258418],"iteration":149,"passed_time":13.79191469,"remaining_time":13.79191469},
{"learn":[1.292082734],"iteration":150,"passed_time":13.88675616,"remaining_time":13.70282561},
{"learn":[1.291637607],"iteration":151,"passed_time":14.00651721,"remaining_time":13.63792465},
{"learn":[1.291183157],"iteration":152,"passed_time":14.10793919,"remaining_time":13.55468667},
{"learn":[1.290655414],"iteration":153,"passed_time":14.1911605,"remaining_time":13.45395736},
{"learn":[1.290136542],"iteration":154,"passed_time":14.28381111,"remaining_time":13.36227491},
{"learn":[1.289579973],"iteration":155,"passed_time":14.37492686,"remaining_time":13.26916326},
{"learn":[1.289123452],"iteration":156,"passed_time":14.46452914,"remaining_time":13.17469851},
{"learn":[1.288626875],"iteration":157,"passed_time":14.54195571,"remaining_time":13.0693526},
{"learn":[1.288182786],"iteration":158,"passed_time":14.61484918,"remaining_time":12.96033795},
{"learn":[1.287550192],"iteration":159,"passed_time":14.70291748,"remaining_time":12.86505279},
{"learn":[1.287192183],"iteration":160,"passed_time":14.80558726,"remaining_time":12.78246353},
{"learn":[1.286721061],"iteration":161,"passed_time":14.89139573,"remaining_time":12.68526303},
{"learn":[1.286277057],"iteration":162,"passed_time":14.98509677,"remaining_time":12.59483594},
{"learn":[1.285800821],"iteration":163,"passed_time":15.06499688,"remaining_time":12.49292424},
{"learn":[1.285212684],"iteration":164,"passed_time":15.1398035,"remaining_time":12.38711195},
{"learn":[1.284759357],"iteration":165,"passed_time":15.23192189,"remaining_time":12.29564779},
{"learn":[1.284277655],"iteration":166,"passed_time":15.31816779,"remaining_time":12.1994989},
{"learn":[1.283872451],"iteration":167,"passed_time":15.41539187,"remaining_time":12.11209361},
{"learn":[1.283554669],"iteration":168,"passed_time":15.49770355,"remaining_time":12.01301281},
{"learn":[1.28317226],"iteration":169,"passed_time":15.59330345,"remaining_time":11.92429087},
{"learn":[1.282731456],"iteration":170,"passed_time":15.68671611,"remaining_time":11.83383847},
{"learn":[1.282365912],"iteration":171,"passed_time":15.77330755,"remaining_time":11.73827539},
{"learn":[1.28195964],"iteration":172,"passed_time":15.86487139,"remaining_time":11.64646628},
{"learn":[1.281620949],"iteration":173,"passed_time":15.95894169,"remaining_time":11.55647501},
{"learn":[1.281279065],"iteration":174,"passed_time":16.04476895,"remaining_time":11.46054925},
{"learn":[1.280906271],"iteration":175,"passed_time":16.13265729,"remaining_time":11.36619036},
{"learn":[1.280539407],"iteration":176,"passed_time":16.20911985,"remaining_time":11.26396464},
{"learn":[1.280170821],"iteration":177,"passed_time":16.31035174,"remaining_time":11.17900512},
{"learn":[1.279845341],"iteration":178,"passed_time":16.43552753,"remaining_time":11.11004933},
{"learn":[1.279542891],"iteration":179,"passed_time":16.53031991,"remaining_time":11.02021327},
{"learn":[1.279217299],"iteration":180,"passed_time":16.6126418,"remaining_time":10.92212361},
{"learn":[1.2788353],"iteration":181,"passed_time":16.70544482,"remaining_time":10.83100269},
{"learn":[1.27851046],"iteration":182,"passed_time":16.79748463,"remaining_time":10.73937542},
{"learn":[1.278240283],"iteration":183,"passed_time":16.89574936,"remaining_time":10.65166807},
{"learn":[1.277915166],"iteration":184,"passed_time":16.9779172,"remaining_time":10.55384042},
{"learn":[1.27765951],"iteration":185,"passed_time":17.07438327,"remaining_time":10.46494459},
{"learn":[1.277337134],"iteration":186,"passed_time":17.14473784,"remaining_time":10.36018917},
{"learn":[1.277010949],"iteration":187,"passed_time":17.23745694,"remaining_time":10.26912329},
{"learn":[1.276725544],"iteration":188,"passed_time":17.32432702,"remaining_time":10.17460476},
{"learn":[1.276426917],"iteration":189,"passed_time":17.41348033,"remaining_time":10.08148861},
{"learn":[1.276155439],"iteration":190,"passed_time":17.50810417,"remaining_time":9.991535887},
{"learn":[1.275887796],"iteration":191,"passed_time":17.58200578,"remaining_time":9.88987825},
{"learn":[1.275644489],"iteration":192,"passed_time":17.6796667,"remaining_time":9.801680503},
{"learn":[1.275359666],"iteration":193,"passed_time":17.75317943,"remaining_time":9.700190823},
{"learn":[1.275070743],"iteration":194,"passed_time":17.82755934,"remaining_time":9.599455027},
{"learn":[1.274858337],"iteration":195,"passed_time":17.92172396,"remaining_time":9.509486185},
{"learn":[1.274561415],"iteration":196,"passed_time":17.99645125,"remaining_time":9.409312075},
{"learn":[1.274341353],"iteration":197,"passed_time":18.10442723,"remaining_time":9.326523117},
{"learn":[1.274004599],"iteration":198,"passed_time":18.19255986,"remaining_time":9.233409778},
{"learn":[1.273837173],"iteration":199,"passed_time":18.31142073,"remaining_time":9.155710366},
{"learn":[1.273606268],"iteration":200,"passed_time":18.40327933,"remaining_time":9.064301759},
{"learn":[1.27337832],"iteration":201,"passed_time":18.50966612,"remaining_time":8.979937028},
{"learn":[1.273144204],"iteration":202,"passed_time":18.6049773,"remaining_time":8.890063047},
{"learn":[1.272916149],"iteration":203,"passed_time":18.69965135,"remaining_time":8.799835932},
{"learn":[1.272660688],"iteration":204,"passed_time":18.78849108,"remaining_time":8.706861719},
{"learn":[1.272437291],"iteration":205,"passed_time":18.88606058,"remaining_time":8.617911141},
{"learn":[1.272188609],"iteration":206,"passed_time":18.96004057,"remaining_time":8.518279096},
{"learn":[1.272007434],"iteration":207,"passed_time":19.0635582,"remaining_time":8.431958433},
{"learn":[1.271786239],"iteration":208,"passed_time":19.15869013,"remaining_time":8.341822018},
{"learn":[1.271570376],"iteration":209,"passed_time":19.25269425,"remaining_time":8.25115468},
{"learn":[1.271352337],"iteration":210,"passed_time":19.3243845,"remaining_time":8.151043699},
{"learn":[1.271168828],"iteration":211,"passed_time":19.41711632,"remaining_time":8.059935075},
{"learn":[1.270966518],"iteration":212,"passed_time":19.51476432,"remaining_time":7.970819231},
{"learn":[1.270749057],"iteration":213,"passed_time":19.60870916,"remaining_time":7.880135456},
{"learn":[1.270530095],"iteration":214,"passed_time":19.69527048,"remaining_time":7.786502281},
{"learn":[1.270308717],"iteration":215,"passed_time":19.78731028,"remaining_time":7.69506511},
{"learn":[1.270219857],"iteration":216,"passed_time":19.88973048,"remaining_time":7.607592764},
{"learn":[1.269958765],"iteration":217,"passed_time":19.97732331,"remaining_time":7.514406016},
{"learn":[1.269786236],"iteration":218,"passed_time":20.07090672,"remaining_time":7.423486048},
{"learn":[1.269608015],"iteration":219,"passed_time":20.15831793,"remaining_time":7.330297428},
{"learn":[1.269450466],"iteration":220,"passed_time":20.25081241,"remaining_time":7.238978191},
{"learn":[1.269271812],"iteration":221,"passed_time":20.32937816,"remaining_time":7.142754489},
{"learn":[1.269138522],"iteration":222,"passed_time":20.40896639,"remaining_time":7.047042205},
{"learn":[1.268989348],"iteration":223,"passed_time":20.48187331,"remaining_time":6.949207017},
{"learn":[1.268808017],"iteration":224,"passed_time":20.56550064,"remaining_time":6.855166878},
{"learn":[1.268710406],"iteration":225,"passed_time":20.66207517,"remaining_time":6.765458242},
{"learn":[1.268563355],"iteration":226,"passed_time":20.73799564,"remaining_time":6.669047056},
{"learn":[1.268352446],"iteration":227,"passed_time":20.82357732,"remaining_time":6.575866522},
{"learn":[1.268169474],"iteration":228,"passed_time":20.91656601,"remaining_time":6.485048852},
{"learn":[1.268019894],"iteration":229,"passed_time":21.00281904,"remaining_time":6.392162316},
{"learn":[1.2678782],"iteration":230,"passed_time":21.10502023,"remaining_time":6.304096952},
{"learn":[1.267675087],"iteration":231,"passed_time":21.19812093,"remaining_time":6.213242341},
{"learn":[1.267492442],"iteration":232,"passed_time":21.29512672,"remaining_time":6.123491374},
{"learn":[1.267357368],"iteration":233,"passed_time":21.37461807,"remaining_time":6.028738429},
{"learn":[1.26723006],"iteration":234,"passed_time":21.47164919,"remaining_time":5.938966797},
{"learn":[1.26710693],"iteration":235,"passed_time":21.54708565,"remaining_time":5.843277465},
{"learn":[1.266950739],"iteration":236,"passed_time":21.63598454,"remaining_time":5.751337663},
{"learn":[1.266828599],"iteration":237,"passed_time":21.73091656,"remaining_time":5.660995069},
{"learn":[1.2666948],"iteration":238,"passed_time":21.82149409,"remaining_time":5.569502677},
{"learn":[1.266524154],"iteration":239,"passed_time":21.91666849,"remaining_time":5.479167121},
{"learn":[1.26632578],"iteration":240,"passed_time":22.00595259,"remaining_time":5.387349389},
{"learn":[1.266135449],"iteration":241,"passed_time":22.09513894,"remaining_time":5.295529168},
{"learn":[1.266029624],"iteration":242,"passed_time":22.19127114,"remaining_time":5.205359897},
{"learn":[1.265891223],"iteration":243,"passed_time":22.2809045,"remaining_time":5.113650213},
{"learn":[1.265711737],"iteration":244,"passed_time":22.37411253,"remaining_time":5.022759956},
{"learn":[1.265606339],"iteration":245,"passed_time":22.47209637,"remaining_time":4.932899204},
{"learn":[1.265470788],"iteration":246,"passed_time":22.57486299,"remaining_time":4.843998942},
{"learn":[1.265307123],"iteration":247,"passed_time":22.66226503,"remaining_time":4.751765248},
{"learn":[1.265166471],"iteration":248,"passed_time":22.7523106,"remaining_time":4.66011181},
{"learn":[1.265106137],"iteration":249,"passed_time":22.86002483,"remaining_time":4.572004965},
{"learn":[1.264988716],"iteration":250,"passed_time":22.93273096,"remaining_time":4.476907638},
{"learn":[1.26486589],"iteration":251,"passed_time":23.01058954,"remaining_time":4.382969436},
{"learn":[1.26473004],"iteration":252,"passed_time":23.16160484,"remaining_time":4.302748725},
{"learn":[1.264611075],"iteration":253,"passed_time":23.2353357,"remaining_time":4.207974181},
{"learn":[1.264470011],"iteration":254,"passed_time":23.32317799,"remaining_time":4.115854939},
{"learn":[1.264349235],"iteration":255,"passed_time":23.39484323,"remaining_time":4.020988681},
{"learn":[1.264242849],"iteration":256,"passed_time":23.47445267,"remaining_time":3.927632158},
{"learn":[1.264140871],"iteration":257,"passed_time":23.57232351,"remaining_time":3.83735499},
{"learn":[1.264035403],"iteration":258,"passed_time":23.66463236,"remaining_time":3.746138714},
{"learn":[1.263923678],"iteration":259,"passed_time":23.75644113,"remaining_time":3.654837097},
{"learn":[1.263806851],"iteration":260,"passed_time":23.85154185,"remaining_time":3.564023495},
{"learn":[1.263720129],"iteration":261,"passed_time":23.93911102,"remaining_time":3.472084804},
{"learn":[1.263649486],"iteration":262,"passed_time":24.03043327,"remaining_time":3.380707343},
{"learn":[1.263542003],"iteration":263,"passed_time":24.11863628,"remaining_time":3.288904947},
{"learn":[1.263446794],"iteration":264,"passed_time":24.1911142,"remaining_time":3.195052819},
{"learn":[1.263342191],"iteration":265,"passed_time":24.27346988,"remaining_time":3.10262397},
{"learn":[1.26326025],"iteration":266,"passed_time":24.36895673,"remaining_time":3.011893529},
{"learn":[1.263136786],"iteration":267,"passed_time":24.46104984,"remaining_time":2.920722368},
{"learn":[1.262994949],"iteration":268,"passed_time":24.5302898,"remaining_time":2.82691072},
{"learn":[1.262907189],"iteration":269,"passed_time":24.63196923,"remaining_time":2.73688547},
{"learn":[1.262794339],"iteration":270,"passed_time":24.72135584,"remaining_time":2.645458743},
{"learn":[1.262693856],"iteration":271,"passed_time":24.81409582,"remaining_time":2.554392217},
{"learn":[1.262621143],"iteration":272,"passed_time":24.91751045,"remaining_time":2.464369165},
{"learn":[1.262460342],"iteration":273,"passed_time":25.00582062,"remaining_time":2.372815096},
{"learn":[1.262390877],"iteration":274,"passed_time":25.10560441,"remaining_time":2.282327674},
{"learn":[1.262271958],"iteration":275,"passed_time":25.19004237,"remaining_time":2.190438467},
{"learn":[1.262154569],"iteration":276,"passed_time":25.27768499,"remaining_time":2.098869151},
{"learn":[1.262057881],"iteration":277,"passed_time":25.37079465,"remaining_time":2.007760727},
{"learn":[1.261969544],"iteration":278,"passed_time":25.44970149,"remaining_time":1.915568929},
{"learn":[1.261887622],"iteration":279,"passed_time":25.52877104,"remaining_time":1.823483646},
{"learn":[1.26182005],"iteration":280,"passed_time":25.64006627,"remaining_time":1.733669961},
{"learn":[1.261748497],"iteration":281,"passed_time":25.74020456,"remaining_time":1.64299178},
{"learn":[1.26167194],"iteration":282,"passed_time":25.81687475,"remaining_time":1.550836999},
{"learn":[1.261626016],"iteration":283,"passed_time":25.9201407,"remaining_time":1.460289617},
{"learn":[1.261621731],"iteration":284,"passed_time":26.0355092,"remaining_time":1.370289958},
{"learn":[1.261506875],"iteration":285,"passed_time":26.12045891,"remaining_time":1.278623863},
{"learn":[1.261501798],"iteration":286,"passed_time":26.21957998,"remaining_time":1.18764648},
{"learn":[1.261407372],"iteration":287,"passed_time":26.31837834,"remaining_time":1.096599097},
{"learn":[1.261311713],"iteration":288,"passed_time":26.42579768,"remaining_time":1.005826209},
{"learn":[1.261224249],"iteration":289,"passed_time":26.53193684,"remaining_time":0.9148943739},
{"learn":[1.261147972],"iteration":290,"passed_time":26.64433046,"remaining_time":0.8240514576},
{"learn":[1.261067594],"iteration":291,"passed_time":26.75999867,"remaining_time":0.7331506485},
{"learn":[1.261038856],"iteration":292,"passed_time":26.85351912,"remaining_time":0.6415516514},
{"learn":[1.261004276],"iteration":293,"passed_time":26.95989408,"remaining_time":0.55020192},
{"learn":[1.260928998],"iteration":294,"passed_time":27.03966218,"remaining_time":0.458299359},
{"learn":[1.260868146],"iteration":295,"passed_time":27.13422686,"remaining_time":0.3666787413},
{"learn":[1.260789765],"iteration":296,"passed_time":27.21975704,"remaining_time":0.2749470408},
{"learn":[1.260711335],"iteration":297,"passed_time":27.31044999,"remaining_time":0.1832916107},
{"learn":[1.260661044],"iteration":298,"passed_time":27.41233364,"remaining_time":0.09168004562},
{"learn":[1.260579417],"iteration":299,"passed_time":27.48604029,"remaining_time":0}
]}